<?xml version="1.0" encoding="UTF-8" ?>
<!-- Generated by Oracle SOA Modeler version 12.2.1.3.0.170820 at [12/1/25 2:16 AM]. -->
<composite name="Arthamatic"
           revision="1.0"
           label="2025-01-12_02-16-06_596"
           mode="active"
           state="on"
           xmlns="http://xmlns.oracle.com/sca/1.0"
           xmlns:xs="http://www.w3.org/2001/XMLSchema"
           xmlns:wsp="http://schemas.xmlsoap.org/ws/2004/09/policy"
           xmlns:orawsp="http://schemas.oracle.com/ws/2006/01/policy"
           xmlns:ui="http://xmlns.oracle.com/soa/designer/"
           xmlns:sca-ext="http://xmlns.oracle.com/sca/1.0-ext">
  <import namespace="http://practice/FMW/Arthamatic/ArthematicBPELProcess" location="WSDLs/ArthematicBPELProcess.wsdl"
          importType="wsdl"/>
  <service name="arthematicbpelprocess_client_ep" ui:wsdlLocation="WSDLs/ArthematicBPELProcess.wsdl">
    <interface.wsdl interface="http://practice/FMW/Arthamatic/ArthematicBPELProcess#wsdl.interface(ArthematicBPELProcess)"
                    callbackInterface="http://practice/FMW/Arthamatic/ArthematicBPELProcess#wsdl.interface(ArthematicBPELProcessCallback)"/>
    <binding.ws port="http://practice/FMW/Arthamatic/ArthematicBPELProcess#wsdl.endpoint(arthematicbpelprocess_client_ep/ArthematicBPELProcess_pt)"/>
    <callback>
      <binding.ws port="http://practice/FMW/Arthamatic/ArthematicBPELProcess#wsdl.endpoint(arthematicbpelprocess_client_ep/ArthematicBPELProcessCallback_pt)"/>
    </callback>
  </service>
  <property name="productVersion" type="xs:string" many="false">12.2.1.3.0.170820</property>
  <property name="compositeID" type="xs:string" many="false">f672dc0d-8c44-4257-a37f-d73f4f512e24</property>
  <component name="ArthematicBPELProcess" version="2.0">
    <implementation.bpel src="BPEL/ArthematicBPELProcess.bpel"/>
    <componentType>
      <service name="arthematicbpelprocess_client" ui:wsdlLocation="WSDLs/ArthematicBPELProcess.wsdl">
        <interface.wsdl interface="http://practice/FMW/Arthamatic/ArthematicBPELProcess#wsdl.interface(ArthematicBPELProcess)"
                        callbackInterface="http://practice/FMW/Arthamatic/ArthematicBPELProcess#wsdl.interface(ArthematicBPELProcessCallback)"/>
      </service>
    </componentType>
    <property name="bpel.config.oneWayDeliveryPolicy" type="xs:string" many="false">async.persist</property>
  </component>
  <wire>
    <source.uri>arthematicbpelprocess_client_ep</source.uri>
    <target.uri>ArthematicBPELProcess/arthematicbpelprocess_client</target.uri>
  </wire>
</composite>
